certbot_dns_aliyun/__init__.py
certbot_dns_aliyun/alidns.py
certbot_dns_aliyun/alidns_test.py
certbot_dns_aliyun/dns_aliyun.py
certbot_dns_aliyun/dns_aliyun_test.py
certbot_dns_aliyun-2.0.0.dist-info/LICENSE.txt
certbot_dns_aliyun-2.0.0.dist-info/METADATA
certbot_dns_aliyun-2.0.0.dist-info/WHEEL
certbot_dns_aliyun-2.0.0.dist-info/entry_points.txt
certbot_dns_aliyun-2.0.0.dist-info/top_level.txt
certbot_dns_aliyun-2.0.0.dist-info/RECORD
